LICENSE
MANIFEST.in
README
setup.py
django_tracked_model.egg-info/PKG-INFO
django_tracked_model.egg-info/SOURCES.txt
django_tracked_model.egg-info/dependency_links.txt
django_tracked_model.egg-info/requires.txt
django_tracked_model.egg-info/top_level.txt
tracked_model/__init__.py
tracked_model/control.py
tracked_model/defs.py
tracked_model/models.py
tracked_model/serializer.py
tracked_model/migrations/0001_initial.py
tracked_model/migrations/__init__.py