Metadata-Version: 1.1
Name: django-tracked-model
Version: 0.1.2
Summary: Track changes to django models
Home-page: https://github.com/ojake/django-tracked-model
Author: Jakub Owczarski
Author-email: jakub3279@gmail.com
License: MIT
Platform: UNKNOWN
Classifier: Development Status :: 4 - Beta
Classifier: Intended Audience :: Developers
Classifier: Programming Language :: Python :: 3
